ezgame/__init__.py
ezgame/example.py
ezgame/ezgame.py
ezgame-0.0.2.dist-info/LICENSE
ezgame-0.0.2.dist-info/METADATA
ezgame-0.0.2.dist-info/WHEEL
ezgame-0.0.2.dist-info/top_level.txt
ezgame-0.0.2.dist-info/RECORD
